{"id":"184022","weekday":2,"bgmurl":"https:\/\/bgm.tv\/subject\/184022","thumb":"https:\/\/lain.bgm.tv\/pic\/cover\/s\/45\/11\/184022_6KkpV.jpg","title":"\u9ad8\u6821\u661f\u6b4c\u5267 \u7b2c\u4e8c\u5b63","status":"1","remark":"","broadcast":{"site":"bilibili","id":"5973","url":"https:\/\/bangumi.bilibili.com\/anime\/5973"},"eps":{"1":{"url":"https:\/\/bangumi.bilibili.com\/anime\/5973\/play#103199","uptime":"00:00"},"2":{"url":"https:\/\/bangumi.bilibili.com\/anime\/5973\/play#103200","uptime":"00:00"}}}