{"id":"200859","weekday":4,"bgmurl":"https:\/\/bgm.tv\/subject\/200859","thumb":"https:\/\/lain.bgm.tv\/pic\/cover\/s\/5f\/2e\/200859_8vfnP.jpg","title":"\u55a7\u54d7\u756a\u957f \u4e59\u5973-Girl Beats Boys-","status":"1","remark":"","broadcast":{"site":"dmhy","id":"%E5%96%A7%E5%93%97%E7%95%AA%E9%95%BF+%E4%B9%99%E5%A5%B3-Girl+Beats+Boys-","url":"https:\/\/share.dmhy.org\/topics\/list?keyword=%E5%96%A7%E5%93%97%E7%95%AA%E9%95%BF+%E4%B9%99%E5%A5%B3-Girl+Beats+Boys-&sort_id=2"},"eps":{"1":{"url":"magnet:?xt=urn:btih:OGGHZ6573GCV66MOULX2HBJYML6GCO5R","uptime":"01:06"}}}